optitrack/NPTrackingToolsx64.dll
optitrack/Qt5Core.dll
optitrack/Qt5Gui.dll
optitrack/Qt5Multimedia.dll
optitrack/Qt5Network.dll
optitrack/Qt5OpenGL.dll
optitrack/Qt5Svg.dll
optitrack/Qt5Widgets.dll
optitrack/ToolKitPro1521vc140x64U.dll
optitrack/__init__.py
optitrack/_optitrack.pyd
optitrack/avcodec-57.dll
optitrack/avfilter-6.dll
optitrack/avformat-57.dll
optitrack/avresample-3.dll
optitrack/avutil-55.dll
optitrack/libiomp5md.dll
optitrack/opencv_world330.dll
optitrack/python36.dll
optitrack/shiboken2.cp36-win_amd64.dll
optitrack/swscale-4.dll
optitrack/tbb.dll
optitrack-0.0.6.dist-info/LICENSE
optitrack-0.0.6.dist-info/METADATA
optitrack-0.0.6.dist-info/WHEEL
optitrack-0.0.6.dist-info/top_level.txt
optitrack-0.0.6.dist-info/RECORD
